README.md
setup.py
teralytic/__init__.py
teralytic/api_client.py
teralytic/configuration.py
teralytic/rest.py
teralytic.egg-info/PKG-INFO
teralytic.egg-info/SOURCES.txt
teralytic.egg-info/dependency_links.txt
teralytic.egg-info/requires.txt
teralytic.egg-info/top_level.txt
teralytic/api/__init__.py
teralytic/api/organization_api.py
teralytic/api/readings_api.py
teralytic/api/telemetry_api.py
teralytic/models/__init__.py
teralytic/models/application.py
teralytic/models/error.py
teralytic/models/field.py
teralytic/models/field_geometry.py
teralytic/models/field_geometry_geometry.py
teralytic/models/micro_climate_data.py
teralytic/models/org_role.py
teralytic/models/organization.py
teralytic/models/probe.py
teralytic/models/property_role.py
teralytic/models/reading.py
teralytic/models/reading_data.py
teralytic/models/reading_location.py
teralytic/models/reading_type.py
teralytic/models/role_permission.py
teralytic/models/sensor_data.py
teralytic/models/string_array.py
teralytic/models/user.py
teralytic/models/uuid_array.py
teralytic/models/weather_data.py
test/__init__.py
test/test_application.py
test/test_error.py
test/test_field.py
test/test_field_geometry.py
test/test_field_geometry_geometry.py
test/test_micro_climate_data.py
test/test_org_role.py
test/test_organization.py
test/test_organization_api.py
test/test_probe.py
test/test_property_role.py
test/test_reading.py
test/test_reading_data.py
test/test_reading_location.py
test/test_reading_type.py
test/test_readings_api.py
test/test_role_permission.py
test/test_sensor_data.py
test/test_string_array.py
test/test_telemetry_api.py
test/test_user.py
test/test_uuid_array.py
test/test_weather_data.py