Metadata-Version: 1.0
Name: teralytic
Version: 1.0.6.post10
Summary: teralytic
Home-page: UNKNOWN
Author: UNKNOWN
Author-email: rob@modelrocket.io
License: UNKNOWN
Keywords: Swagger,teralytic
Platform: UNKNOWN
